py_bmi.py
Py_bmi-1.0.9.dist-info/LICENSE
Py_bmi-1.0.9.dist-info/METADATA
Py_bmi-1.0.9.dist-info/WHEEL
Py_bmi-1.0.9.dist-info/top_level.txt
Py_bmi-1.0.9.dist-info/RECORD
